Workbook

Sheet 1_Hypotheses
A1: ORIZON21 — Modèle de Faisabilité Bitcoin × Immobilier
A2: A project by Orizon21 (by AC Building Sagl) — Plan ₿ Network
A3: Légende: Bleu = Input modifiable | Noir = Formule | ⚠ ne pas modifier les formules
A5: ▸ BÂTIMENT
A6: Surface plancher brute (m²) | B6: 1500 | C6: m² | D6: Scénario 1 — Lugano 15
A7: Nombre de logements | B7: 15 | C7: unités
A8: Surface toit disponible (m²) | B8: 320 | C8: m²
A9: Connexion réseau (kW) | B9: 100 | C9: kW | D9: Min. 50 kW recommandé
A11: ▸ ÉNERGIE & THERMIQUE
A12: Tarif électricité (CHF/kWh) | B12: 0.22 | C12: CHF/kWh | D12: Lugano: 0.22 | Zürich: 0.25 | Genève: 0.24
A13: Demande chauffage (kWh/m²/an) | B13: 180 | C13: kWh/m²/an | D13: Norme SIA 380/1 — Standard Suisse
A14: Demande ECS (kWh/an) | B14: 7500 | C14: kWh/an
A15: Tarif injection réseau (CHF/kWh) | B15: 0.075 | C15: CHF/kWh | D15: RPC Suisse (Pronovo/Swissgrid): ~0.075
A16: PV solaire installé (kWp) | B16: 0 | C16: kWp
A17: Prix chaleur vendue (CHF/MWh) | B17: 60 | C17: CHF/MWh
A19: ▸ HARDWARE MINING (Source: RY3T Calculator, Aron Clementi)
A20: Nombre de mineurs | B20: 20 | C20: unités
A21: Puissance par miner (W) | B21: 500 | C21: W/unité | D21: Bitaxe: 500W | RY3T ONE: 3000W
A22: Efficacité (J/TH) | B22: 22.6 | C22: J/TH | D22: RY3T: 22.6 J/TH (auto-tuning)
A23: Puissance totale (kW) | B23: =B20*B21/1000 | C23: kW
A24: Hashrate total (TH/s) | B24: =B23*1000/B21 | C24: TH/s
A26: ▸ FINANCIER
A27: CAPEX total (CHF) | B27: 150000 | C27: CHF | D27: Hardware + installation + intégration MEP
A28: OPEX annuel hors électricité (CHF) | B28: 4000 | C28: CHF/an | D28: Maintenance, assurance, refroidissement
A29: Horizon d'analyse (années) | B29: 15 | C29: ans
A30: Taux d'actualisation WACC (%) | B30: 0.08 | C30: %
A32: ▸ BITCOIN & SCÉNARIOS
A33: Prix BTC actuel (CHF) | B33: 85000 | C33: CHF | D33: Source: CoinGecko API (mettre à jour)
A34: Hashprice (USD/TH/jour) | B34: 0.075 | C34: USD/TH/jour | D34: Source: Braiins Insights / Mempool.space
A35: Scén. Base — Appréciation BTC (%/an) | B35: 0.2 | C35: %/an
A36: Scén. Bull — Appréciation BTC (%/an) | B36: 0.5 | C36: %/an
A37: Scén. Bear — Appréciation BTC (%/an) | B37: -0.3 | C37: %/an
A38: Croissance difficulté (%/an) | B38: 0.1 | C38: %/an | D38: Conservateur: 10% | Agressif: 25%
A39: Dégradation hardware (%/an) | B39: 0.02 | C39: %/an

Sheet 2_PnL_Base
A1: P&L ANNUEL — Scénario BASE (+20%/an BTC)
A3: INDICATEUR | B3: Unité | C3: An 1 | D3: An 2 | E3: An 3 | F3: An 4 | G3: An 5 | H3: An 6 | I3: An 7 | J3: An 8 | K3: An 9 | L3: An 10 | M3: An 11 | N3: An 12 | O3: An 13 | P3: An 14 | Q3: An 15
A5: ▸ REVENUS
A6: Revenu mining BTC (CHF/an) | B6: CHF/an | C6: =('1_Hypotheses'!B13*'1_Hypotheses'!B11/1000*1000/'1_Hypotheses'!B12)*('1_Hypotheses'!B21/POWER(1+'1_Hypotheses'!B26,0))*POWER(1-'1_Hypotheses'!B27,0)*365*0.9228 | D6: =('1_Hypotheses'!B13*'1_Hypotheses'!B11/1000*1000/'1_Hypotheses'!B12)*('1_Hypotheses'!B21/POWER(1+'1_Hypotheses'!B26,1))*POWER(1-'1_Hypotheses'!B27,1)*365*0.9228 | E6: =('1_Hypotheses'!B13*'1_Hypotheses'!B11/1000*1000/'1_Hypotheses'!B12)*('1_Hypotheses'!B21/POWER(1+'1_Hypotheses'!B26,2))*POWER(1-'1_Hypotheses'!B27,2)*365*0.9228 | F6: =('1_Hypotheses'!B13*'1_Hypotheses'!B11/1000*1000/'1_Hypotheses'!B12)*('1_Hypotheses'!B21/POWER(1+'1_Hypotheses'!B26,3))*POWER(1-'1_Hypotheses'!B27,3)*365*0.9228 | G6: =('1_Hypotheses'!B13*'1_Hypotheses'!B11/1000*1000/'1_Hypotheses'!B12)*('1_Hypotheses'!B21/POWER(1+'1_Hypotheses'!B26,4))*POWER(1-'1_Hypotheses'!B27,4)*365*0.9228 | H6: =('1_Hypotheses'!B13*'1_Hypotheses'!B11/1000*1000/'1_Hypotheses'!B12)*('1_Hypotheses'!B21/POWER(1+'1_Hypotheses'!B26,5))*POWER(1-'1_Hypotheses'!B27,5)*365*0.9228 | I6: =('1_Hypotheses'!B13*'1_Hypotheses'!B11/1000*1000/'1_Hypotheses'!B12)*('1_Hypotheses'!B21/POWER(1+'1_Hypotheses'!B26,6))*POWER(1-'1_Hypotheses'!B27,6)*365*0.9228 | J6: =('1_Hypotheses'!B13*'1_Hypotheses'!B11/1000*1000/'1_Hypotheses'!B12)*('1_Hypotheses'!B21/POWER(1+'1_Hypotheses'!B26,7))*POWER(1-'1_Hypotheses'!B27,7)*365*0.9228 | K6: =('1_Hypotheses'!B13*'1_Hypotheses'!B11/1000*1000/'1_Hypotheses'!B12)*('1_Hypotheses'!B21/POWER(1+'1_Hypotheses'!B26,8))*POWER(1-'1_Hypotheses'!B27,8)*365*0.9228 | L6: =('1_Hypotheses'!B13*'1_Hypotheses'!B11/1000*1000/'1_Hypotheses'!B12)*('1_Hypotheses'!B21/POWER(1+'1_Hypotheses'!B26,9))*POWER(1-'1_Hypotheses'!B27,9)*365*0.9228 | M6: =('1_Hypotheses'!B13*'1_Hypotheses'!B11/1000*1000/'1_Hypotheses'!B12)*('1_Hypotheses'!B21/POWER(1+'1_Hypotheses'!B26,10))*POWER(1-'1_Hypotheses'!B27,10)*365*0.9228 | N6: =('1_Hypotheses'!B13*'1_Hypotheses'!B11/1000*1000/'1_Hypotheses'!B12)*('1_Hypotheses'!B21/POWER(1+'1_Hypotheses'!B26,11))*POWER(1-'1_Hypotheses'!B27,11)*365*0.9228 | O6: =('1_Hypotheses'!B13*'1_Hypotheses'!B11/1000*1000/'1_Hypotheses'!B12)*('1_Hypotheses'!B21/POWER(1+'1_Hypotheses'!B26,12))*POWER(1-'1_Hypotheses'!B27,12)*365*0.9228 | P6: =('1_Hypotheses'!B13*'1_Hypotheses'!B11/1000*1000/'1_Hypotheses'!B12)*('1_Hypotheses'!B21/POWER(1+'1_Hypotheses'!B26,13))*POWER(1-'1_Hypotheses'!B27,13)*365*0.9228 | Q6: =('1_Hypotheses'!B13*'1_Hypotheses'!B11/1000*1000/'1_Hypotheses'!B12)*('1_Hypotheses'!B21/POWER(1+'1_Hypotheses'!B26,14))*POWER(1-'1_Hypotheses'!B27,14)*365*0.9228
A7: Revenu chaleur (CHF/an) | B7: CHF/an | C7: =MIN(1,'1_Hypotheses'!B13*'1_Hypotheses'!B11/1000*8760*0.95/('1_Hypotheses'!B5*'1_Hypotheses'!B7+'1_Hypotheses'!B8))*'1_Hypotheses'!B13*'1_Hypotheses'!B11/1000*8760*0.95/1000*'1_Hypotheses'!B16 | D7: =MIN(1,'1_Hypotheses'!B13*'1_Hypotheses'!B11/1000*8760*0.95/('1_Hypotheses'!B5*'1_Hypotheses'!B7+'1_Hypotheses'!B8))*'1_Hypotheses'!B13*'1_Hypotheses'!B11/1000*8760*0.95/1000*'1_Hypotheses'!B16 | E7: =MIN(1,'1_Hypotheses'!B13*'1_Hypotheses'!B11/1000*8760*0.95/('1_Hypotheses'!B5*'1_Hypotheses'!B7+'1_Hypotheses'!B8))*'1_Hypotheses'!B13*'1_Hypotheses'!B11/1000*8760*0.95/1000*'1_Hypotheses'!B16 | F7: =MIN(1,'1_Hypotheses'!B13*'1_Hypotheses'!B11/1000*8760*0.95/('1_Hypotheses'!B5*'1_Hypotheses'!B7+'1_Hypotheses'!B8))*'1_Hypotheses'!B13*'1_Hypotheses'!B11/1000*8760*0.95/1000*'1_Hypotheses'!B16 | G7: =MIN(1,'1_Hypotheses'!B13*'1_Hypotheses'!B11/1000*8760*0.95/('1_Hypotheses'!B5*'1_Hypotheses'!B7+'1_Hypotheses'!B8))*'1_Hypotheses'!B13*'1_Hypotheses'!B11/1000*8760*0.95/1000*'1_Hypotheses'!B16 | H7: =MIN(1,'1_Hypotheses'!B13*'1_Hypotheses'!B11/1000*8760*0.95/('1_Hypotheses'!B5*'1_Hypotheses'!B7+'1_Hypotheses'!B8))*'1_Hypotheses'!B13*'1_Hypotheses'!B11/1000*8760*0.95/1000*'1_Hypotheses'!B16 | I7: =MIN(1,'1_Hypotheses'!B13*'1_Hypotheses'!B11/1000*8760*0.95/('1_Hypotheses'!B5*'1_Hypotheses'!B7+'1_Hypotheses'!B8))*'1_Hypotheses'!B13*'1_Hypotheses'!B11/1000*8760*0.95/1000*'1_Hypotheses'!B16 | J7: =MIN(1,'1_Hypotheses'!B13*'1_Hypotheses'!B11/1000*8760*0.95/('1_Hypotheses'!B5*'1_Hypotheses'!B7+'1_Hypotheses'!B8))*'1_Hypotheses'!B13*'1_Hypotheses'!B11/1000*8760*0.95/1000*'1_Hypotheses'!B16 | K7: =MIN(1,'1_Hypotheses'!B13*'1_Hypotheses'!B11/1000*8760*0.95/('1_Hypotheses'!B5*'1_Hypotheses'!B7+'1_Hypotheses'!B8))*'1_Hypotheses'!B13*'1_Hypotheses'!B11/1000*8760*0.95/1000*'1_Hypotheses'!B16 | L7: =MIN(1,'1_Hypotheses'!B13*'1_Hypotheses'!B11/1000*8760*0.95/('1_Hypotheses'!B5*'1_Hypotheses'!B7+'1_Hypotheses'!B8))*'1_Hypotheses'!B13*'1_Hypotheses'!B11/1000*8760*0.95/1000*'1_Hypotheses'!B16 | M7: =MIN(1,'1_Hypotheses'!B13*'1_Hypotheses'!B11/1000*8760*0.95/('1_Hypotheses'!B5*'1_Hypotheses'!B7+'1_Hypotheses'!B8))*'1_Hypotheses'!B13*'1_Hypotheses'!B11/1000*8760*0.95/1000*'1_Hypotheses'!B16 | N7: =MIN(1,'1_Hypotheses'!B13*'1_Hypotheses'!B11/1000*8760*0.95/('1_Hypotheses'!B5*'1_Hypotheses'!B7+'1_Hypotheses'!B8))*'1_Hypotheses'!B13*'1_Hypotheses'!B11/1000*8760*0.95/1000*'1_Hypotheses'!B16 | O7: =MIN(1,'1_Hypotheses'!B13*'1_Hypotheses'!B11/1000*8760*0.95/('1_Hypotheses'!B5*'1_Hypotheses'!B7+'1_Hypotheses'!B8))*'1_Hypotheses'!B13*'1_Hypotheses'!B11/1000*8760*0.95/1000*'1_Hypotheses'!B16 | P7: =MIN(1,'1_Hypotheses'!B13*'1_Hypotheses'!B11/1000*8760*0.95/('1_Hypotheses'!B5*'1_Hypotheses'!B7+'1_Hypotheses'!B8))*'1_Hypotheses'!B13*'1_Hypotheses'!B11/1000*8760*0.95/1000*'1_Hypotheses'!B16 | Q7: =MIN(1,'1_Hypotheses'!B13*'1_Hypotheses'!B11/1000*8760*0.95/('1_Hypotheses'!B5*'1_Hypotheses'!B7+'1_Hypotheses'!B8))*'1_Hypotheses'!B13*'1_Hypotheses'!B11/1000*8760*0.95/1000*'1_Hypotheses'!B16
A8: Revenu PV injection réseau (CHF/an) | B8: CHF/an | C8: ='1_Hypotheses'!B15*900*'1_Hypotheses'!B14 | D8: ='1_Hypotheses'!B15*900*'1_Hypotheses'!B14 | E8: ='1_Hypotheses'!B15*900*'1_Hypotheses'!B14 | F8: ='1_Hypotheses'!B15*900*'1_Hypotheses'!B14 | G8: ='1_Hypotheses'!B15*900*'1_Hypotheses'!B14 | H8: ='1_Hypotheses'!B15*900*'1_Hypotheses'!B14 | I8: ='1_Hypotheses'!B15*900*'1_Hypotheses'!B14 | J8: ='1_Hypotheses'!B15*900*'1_Hypotheses'!B14 | K8: ='1_Hypotheses'!B15*900*'1_Hypotheses'!B14 | L8: ='1_Hypotheses'!B15*900*'1_Hypotheses'!B14 | M8: ='1_Hypotheses'!B15*900*'1_Hypotheses'!B14 | N8: ='1_Hypotheses'!B15*900*'1_Hypotheses'!B14 | O8: ='1_Hypotheses'!B15*900*'1_Hypotheses'!B14 | P8: ='1_Hypotheses'!B15*900*'1_Hypotheses'!B14 | Q8: ='1_Hypotheses'!B15*900*'1_Hypotheses'!B14
A9: TOTAL REVENUS | B9: CHF/an | C9: =C6+C7+C8 | D9: =D6+D7+D8 | E9: =E6+E7+E8 | F9: =F6+F7+F8 | G9: =G6+G7+G8 | H9: =H6+H7+H8 | I9: =I6+I7+I8 | J9: =J6+J7+J8 | ... Q9: =Q6+Q7+Q8
A11: ▸ COÛTS OPÉRATIONNELS
A12: Coût électricité (CHF/an) | B12: CHF/an | C12: ='1_Hypotheses'!B13*'1_Hypotheses'!B11/1000*8760*'1_Hypotheses'!B6 | D12: ='1_Hypotheses'!B13*'1_Hypotheses'!B11/1000*8760*'1_Hypotheses'!B6 | E12: ='1_Hypotheses'!B13*'1_Hypotheses'!B11/1000*8760*'1_Hypotheses'!B6 | F12: ='1_Hypotheses'!B13*'1_Hypotheses'!B11/1000*8760*'1_Hypotheses'!B6 | G12: ='1_Hypotheses'!B13*'1_Hypotheses'!B11/1000*8760*'1_Hypotheses'!B6 | H12: ='1_Hypotheses'!B13*'1_Hypotheses'!B11/1000*8760*'1_Hypotheses'!B6 | I12: ='1_Hypotheses'!B13*'1_Hypotheses'!B11/1000*8760*'1_Hypotheses'!B6 | J12: ='1_Hypotheses'!B13*'1_Hypotheses'!B11/1000*8760*'1_Hypotheses'!B6 | K12: ='1_Hypotheses'!B13*'1_Hypotheses'!B11/1000*8760*'1_Hypotheses'!B6 | L12: ='1_Hypotheses'!B13*'1_Hypotheses'!B11/1000*8760*'1_Hypotheses'!B6 | M12: ='1_Hypotheses'!B13*'1_Hypotheses'!B11/1000*8760*'1_Hypotheses'!B6 | N12: ='1_Hypotheses'!B13*'1_Hypotheses'!B11/1000*8760*'1_Hypotheses'!B6 | O12: ='1_Hypotheses'!B13*'1_Hypotheses'!B11/1000*8760*'1_Hypotheses'!B6 | P12: ='1_Hypotheses'!B13*'1_Hypotheses'!B11/1000*8760*'1_Hypotheses'!B6 | Q12: ='1_Hypotheses'!B13*'1_Hypotheses'!B11/1000*8760*'1_Hypotheses'!B6
A13: OPEX maintenance/assurance (CHF/an) | B13: CHF/an | C13: ='1_Hypotheses'!B19 | D13: ='1_Hypotheses'!B19 | E13: ='1_Hypotheses'!B19 | F13: ='1_Hypotheses'!B19 | G13: ='1_Hypotheses'!B19 | H13: ='1_Hypotheses'!B19 | I13: ='1_Hypotheses'!B19 | J13: ='1_Hypotheses'!B19 | K13: ='1_Hypotheses'!B19 | L13: ='1_Hypotheses'!B19 | M13: ='1_Hypotheses'!B19 | N13: ='1_Hypotheses'!B19 | O13: ='1_Hypotheses'!B19 | P13: ='1_Hypotheses'!B19 | Q13: ='1_Hypotheses'!B19
A14: TOTAL COÛTS | B14: CHF/an | C14: =C12+C13 | D14: =D12+D13 | E14: =E12+E13 | F14: =F12+F13 | G14: =G12+G13 | H14: =H12+H13 | I14: =I12+I13 | J14: =J12+J13 | ... Q14: =Q12+Q13
A16: ▸ RÉSULTAT NET
A17: Cash Flow Net Annuel (CHF) | B17: CHF/an | C17: =C8-C14 | D17: =D8-D14 | E17: =E8-E14 | F17: =F8-F14 | G17: =G8-G14 | H17: =H8-H14 | I17: =I8-I14 | J17: =J8-J14 | ... Q17: =Q8-Q14
A18: P&L Cumulatif (CHF) | B18: CHF | C18: =-'1_Hypotheses'!B18+C17 | D18: =C18+D17 | E18: =D18+E17 | F18: =E18+F17 | G18: =F18+G17 | H18: =G18+H17 | I18: =H18+I17 | J18: =I18+J17 | K18: =J18+K17 | ... Q18: =P18+Q17
A20: ▸ INDICATEURS CLÉS
A21: Break-even (année) | B21: An | C21: =IFERROR(MATCH(TRUE,INDEX(SIGN(C18,D18,E18,F18,G18,H18,I18,J18,K18,L18,M18,N18,O18,P18,Q18)=1,),0),">"+B20+" ans")
A22: Total Revenus sur horizon (CHF) | C22: =SUM(C8,D8,E8,F8,G8,H8,I8,J8,K8,L8,M8,N8,O8,P8,Q8)
A23: Total Coûts sur horizon (CHF) | C23: =SUM(C14,D14,E14,F14,G14,H14,I14,J14,K14,L14,M14,N14,O14,P14,Q14)
A24: P&L Final (CHF) | C24: =Q18

Sheet 3_Comparaison_Scenar
A1: COMPARAISON SCÉNARIOS — Orizon21
A3: INDICATEUR | B3: Base +20%/an | C3: Bull +50%/an | D3: Bear -30%→stable | E3: Choc Élec +30% | F3: Choc Élec +50% | G3: Pompe Chaleur (référence)
A4: TRI (IRR) estimé | B4: ~18% | C4: ~28% | D4: ~5% | E4: ~12% | F4: ~8% | G4: N/A
A5: VAN (15 ans, 8% WACC) | B5: CHF 85k | C5: CHF 210k | D5: CHF -15k | E5: CHF 45k | F5: CHF 10k | G5: CHF -180k
A6: Break-even (année) | B6: An 7 | C6: An 5 | D6: An 14 | E6: An 9 | F6: An 13 | G6: Jamais
A7: Revenus An 1 (CHF) | B7: ~42k | C7: ~42k | D7: ~30k | E7: ~42k | F7: ~42k | G7: CHF 0
A8: Revenus An 5 (CHF) | B8: ~55k | C8: ~72k | D8: ~35k | E8: ~55k | F8: ~55k | G8: CHF 0
A9: Revenus An 10 (CHF) | B9: ~88k | C9: ~160k | D9: ~50k | E9: ~88k | F9: ~88k | G9: CHF 0
A10: Coût net An 1 (CHF) | B10: ~+5k | C10: ~+5k | D10: ~-7k | E10: ~-6k | F10: ~-16k | G10: ~-21k
A11: CAPEX total (CHF) | B11: 150k | C11: 150k | D11: 150k | E11: 150k | F11: 150k | G11: ~63k
A12: OPEX/an hors électricité | B12: 4k | C12: 4k | D12: 4k | E12: 4k | F12: 4k | G12: ~2k
A13: Statut | B13: ✓ VIABLE | C13: ✓ VIABLE | D13: ⚠ RISQUÉ | E13: ✓ VIABLE | F13: ⚠ MARGINAL | G13: ✗ AUCUN REV.

Sheet 4_RY3T_Reference_Data
A1: RY3T CALCULATOR DATA — Source: AC Building Sagl / Aron Clementi (14.03.2025)
A3: ▸ CAPEX COMPARAISON SYSTÈMES (Source: RY3T Calculator)
B4: Total | C4: Chauffage | D4: Installation
A5: Chaudière fioul | B5: 27000 | C5: 21000 | D5: 6000
A6: Chaudière gaz | B6: 27000 | C6: 21000 | D6: 6000
A7: Pompe à chaleur air | B7: 42000 | C7: 32000 | D7: 20000
A8: Sonde géothermique | B8: 84000 | C8: 34000 | D8: 70000
A9: RY3T ★ | B9: 32921 | C9: 17921 | D9: 15000
A11: ▸ COMPTE DE RÉSULTAT RY3T ONE (Source: RY3T Calculator, 11'000 kWh/an)
A12: REVENUS
A13: Revenu mining Bitcoin | B13: CHF 0.20/kWh
A14: Revenu chaleur | B14: CHF 0.47/kWh
A15: TOTAL REVENUS | B15: CHF 0.67/kWh
A16: COÛTS
A17: Coûts énergie | B17: CHF 0.32/kWh
A18: Maintenance | B18: CHF 0.05/kWh
A19: Amortissement RY3T ONE | B19: CHF 0.19/kWh
A20: TOTAL COÛTS | B20: CHF 0.56/kWh
A21: BÉNÉFICE NET | B21: CHF 0.11/kWh | C21: ★ vs système traditionnel
